{
  "lessons": [
    {
      "id": 1,
      "title": "Keep your goals to yourself | Derek Sivers",
      "youtube_url": "https://www.youtube.com/watch?v=NHopJHSlVo4",
      "level": "B1",
      "total_sentences": 64,
      "sentences": [
        {
          "id": 1,
          "lesson_id": 1,
          "index": 0,
          "text": "Everyone, please think of your biggest personal goal.",
          "translation": "Mọi người, xin hãy nghĩ về mục tiêu cá nhân lớn nhất của bạn.",
          "start_time": 16.371,
          "end_time": 19.386,
          "normalized_text": "everyone, please think of your biggest personal goal."
        },
        {
          "id": 2,
          "lesson_id": 1,
          "index": 1,
          "text": "For real -- you can take a second. You've got to feel this to learn it.",
          "translation": "Thật đấy -- bạn có thể dành ra một giây. Bạn phải cảm nhận được điều này để học nó.",
          "start_time": 20.117,
          "end_time": 23.665,
          "normalized_text": "for real you can take a second. you have got to feel this to learn it."
        },
        {
          "id": 3,
          "lesson_id": 1,
          "index": 2,
          "text": "Take a few seconds and think of your personal biggest goal, okay?",
          "translation": "Hãy dành vài giây và nghĩ về mục tiêu cá nhân lớn nhất của bạn, được chứ?",
          "start_time": 23.689,
          "end_time": 26.99,
          "normalized_text": "take a few seconds and think of your personal biggest goal, okay?"
        },
        {
          "id": 4,
          "lesson_id": 1,
          "index": 3,
          "text": "Imagine deciding right now that you're going to do it.",
          "translation": "Hãy tưởng tượng bạn quyết định ngay bây giờ rằng bạn sẽ thực hiện nó.",
          "start_time": 27.427,
          "end_time": 30.108,
          "normalized_text": "imagine deciding right now that you are going to do it."
        },
        {
          "id": 5,
          "lesson_id": 1,
          "index": 4,
          "text": "Imagine telling someone that you meet today what you're going to do.",
          "translation": "Hãy tưởng tượng bạn kể cho một người bạn gặp hôm nay về điều bạn sẽ làm.",
          "start_time": 30.132,
          "end_time": 33.401,
          "normalized_text": "imagine telling someone that you meet today what you are going to do."
        },
        {
          "id": 6,
          "lesson_id": 1,
          "index": 5,
          "text": "Imagine their congratulations,",
          "translation": "Hãy tưởng tượng lời chúc mừng của họ,",
          "start_time": 33.425,
          "end_time": 35.66,
          "normalized_text": "imagine their congratulations,"
        },
        {
          "id": 7,
          "lesson_id": 1,
          "index": 6,
          "text": "and their high image of you.",
          "translation": "và hình ảnh tốt đẹp của họ về bạn.",
          "start_time": 35.684,
          "end_time": 37.236,
          "normalized_text": "and their high image of you."
        },
        {
          "id": 8,
          "lesson_id": 1,
          "index": 7,
          "text": "Doesn't it feel good to say it out loud?",
          "translation": "Nói ra thành lời có cảm thấy tuyệt vời không?",
          "start_time": 37.26,
          "end_time": 39.609,
          "normalized_text": "does not it feel good to say it out loud?"
        },
        {
          "id": 9,
          "lesson_id": 1,
          "index": 8,
          "text": "Don't you feel one step closer already,",
          "translation": "Bạn có cảm thấy mình đã tiến gần hơn một bước rồi không,",
          "start_time": 39.633,
          "end_time": 42.099,
          "normalized_text": "do not you feel one step closer already,"
        },
        {
          "id": 10,
          "lesson_id": 1,
          "index": 9,
          "text": "like it's already becoming part of your identity?",
          "translation": "giống như nó đã trở thành một phần con người của bạn?",
          "start_time": 42.123,
          "end_time": 44.577,
          "normalized_text": "like it is already becoming part of your identity?"
        },
        {
          "id": 11,
          "lesson_id": 1,
          "index": 10,
          "text": "Well, bad news: you should have kept your mouth shut,",
          "translation": "Chà, tin buồn đây: lẽ ra bạn nên giữ im lặng,",
          "start_time": 44.601,
          "end_time": 48.597,
          "normalized_text": "well, bad news you should have kept your mouth shut,"
        },
        {
          "id": 12,
          "lesson_id": 1,
          "index": 11,
          "text": "because that good feeling",
          "translation": "bởi vì cảm giác tốt đẹp đó",
          "start_time": 48.621,
          "end_time": 50.05,
          "normalized_text": "because that good feeling"
        },
        {
          "id": 13,
          "lesson_id": 1,
          "index": 12,
          "text": "now will make you less likely to do it.",
          "translation": "bây giờ sẽ khiến bạn ít có khả năng thực hiện nó hơn.",
          "start_time": 50.074,
          "end_time": 52.145,
          "normalized_text": "now will make you less likely to do it."
        },
        {
          "id": 14,
          "lesson_id": 1,
          "index": 13,
          "text": "The repeated psychology tests have proven",
          "translation": "Các bài kiểm tra tâm lý học được lặp lại đã chứng minh rằng",
          "start_time": 52.755,
          "end_time": 55.081,
          "normalized_text": "the repeated psychology tests have proven"
        },
        {
          "id": 15,
          "lesson_id": 1,
          "index": 14,
          "text": "that telling someone your goal makes it less likely to happen.",
          "translation": "việc nói cho ai đó biết mục tiêu của bạn sẽ khiến nó ít có khả năng xảy ra hơn.",
          "start_time": 55.105,
          "end_time": 58.453,
          "normalized_text": "that telling someone your goal makes it less likely to happen."
        },
        {
          "id": 16,
          "lesson_id": 1,
          "index": 15,
          "text": "Any time you have a goal,",
          "translation": "Bất cứ khi nào bạn có một mục tiêu,",
          "start_time": 59.366,
          "end_time": 60.671,
          "normalized_text": "any time you have a goal,"
        },
        {
          "id": 17,
          "lesson_id": 1,
          "index": 16,
          "text": "there are some steps that need to be done,",
          "translation": "sẽ có một vài bước cần phải được thực hiện,",
          "start_time": 60.695,
          "end_time": 62.719,
          "normalized_text": "there are some steps that need to be done,"
        },
        {
          "id": 18,
          "lesson_id": 1,
          "index": 17,
          "text": "some work that needs to be done in order to achieve it.",
          "translation": "một số công việc cần phải được hoàn thành để đạt được nó.",
          "start_time": 62.743,
          "end_time": 65.324,
          "normalized_text": "some work that needs to be done in order to achieve it."
        },
        {
          "id": 19,
          "lesson_id": 1,
          "index": 18,
          "text": "Ideally you would not be satisfied until you'd actually done the work.",
          "translation": "Lý tưởng nhất là bạn sẽ không hài lòng cho đến khi bạn thực sự hoàn thành công việc.",
          "start_time": 65.348,
          "end_time": 68.644,
          "normalized_text": "ideally you would not be satisfied until you would actually done the work."
        },
        {
          "id": 20,
          "lesson_id": 1,
          "index": 19,
          "text": "But when you tell someone your goal and they acknowledge it,",
          "translation": "Nhưng khi bạn nói cho ai đó về mục tiêu của mình và họ công nhận điều đó,",
          "start_time": 68.668,
          "end_time": 71.53999999999999,
          "normalized_text": "but when you tell someone your goal and they acknowledge it,"
        },
        {
          "id": 21,
          "lesson_id": 1,
          "index": 20,
          "text": "psychologists have found that it's called a \"social reality.\"",
          "translation": "các nhà tâm lý học đã phát hiện ra rằng nó được gọi là một \"thực tế xã hội.\"",
          "start_time": 71.564,
          "end_time": 74.467,
          "normalized_text": "psychologists have found that it is called a social reality."
        },
        {
          "id": 22,
          "lesson_id": 1,
          "index": 21,
          "text": "The mind is kind of tricked into feeling that it's already done.",
          "translation": "Tâm trí bị đánh lừa và cảm thấy rằng việc đó đã được hoàn thành rồi.",
          "start_time": 74.491,
          "end_time": 77.501,
          "normalized_text": "the mind is kind of tricked into feeling that it is already done."
        },
        {
          "id": 23,
          "lesson_id": 1,
          "index": 22,
          "text": "And then because you've felt that satisfaction,",
          "translation": "Và rồi bởi vì bạn đã cảm thấy sự thỏa mãn đó,",
          "start_time": 77.525,
          "end_time": 79.78,
          "normalized_text": "and then because you have felt that satisfaction,"
        },
        {
          "id": 24,
          "lesson_id": 1,
          "index": 23,
          "text": "you're less motivated to do the actual hard work necessary.",
          "translation": "bạn sẽ ít có động lực hơn để thực hiện công việc khó khăn cần thiết.",
          "start_time": 79.804,
          "end_time": 82.752,
          "normalized_text": "you are less motivated to do the actual hard work necessary."
        },
        {
          "id": 25,
          "lesson_id": 1,
          "index": 24,
          "text": "So this goes against conventional wisdom",
          "translation": "Vậy, điều này đi ngược lại với quan niệm thông thường",
          "start_time": 84.10900000000001,
          "end_time": 86.14099999999999,
          "normalized_text": "so this goes against conventional wisdom"
        },
        {
          "id": 26,
          "lesson_id": 1,
          "index": 25,
          "text": "that we should tell our friends our goals, right?",
          "translation": "rằng chúng ta nên nói cho bạn bè biết mục tiêu của mình, phải không?",
          "start_time": 86.16499999999999,
          "end_time": 88.554,
          "normalized_text": "that we should tell our friends our goals, right?"
        },
        {
          "id": 27,
          "lesson_id": 1,
          "index": 26,
          "text": "So they hold us to it.",
          "translation": "Để họ có thể nhắc nhở chúng ta thực hiện.",
          "start_time": 88.578,
          "end_time": 91.10300000000001,
          "normalized_text": "so they hold us to it."
        },
        {
          "id": 28,
          "lesson_id": 1,
          "index": 27,
          "text": "So, let's look at the proof.",
          "translation": "Vậy, chúng ta hãy xem xét bằng chứng.",
          "start_time": 91.127,
          "end_time": 93.23599999999999,
          "normalized_text": "so, lets look at the proof."
        },
        {
          "id": 29,
          "lesson_id": 1,
          "index": 28,
          "text": "1926: Kurt Lewin, founder of social psychology,",
          "translation": "Năm 1926: Kurt Lewin, người sáng lập ngành tâm lý học xã hội,",
          "start_time": 93.25999999999999,
          "end_time": 96.086,
          "normalized_text": "1926 kurt lewin, founder of social psychology,"
        },
        {
          "id": 30,
          "lesson_id": 1,
          "index": 29,
          "text": "called this \"substitution.\"",
          "translation": "đã gọi đây là \"sự thay thế.\"",
          "start_time": 96.11,
          "end_time": 97.59,
          "normalized_text": "called this substitution."
        },
        {
          "id": 31,
          "lesson_id": 1,
          "index": 30,
          "text": "1933: Wera Mahler found when it was acknowledged by others,",
          "translation": "Năm 1933: Wera Mahler phát hiện ra rằng khi được người khác công nhận,",
          "start_time": 97.614,
          "end_time": 100.979,
          "normalized_text": "1933 wera mahler found when it was acknowledged by others,"
        },
        {
          "id": 32,
          "lesson_id": 1,
          "index": 31,
          "text": "it felt real in the mind.",
          "translation": "nó có cảm giác như thật trong tâm trí.",
          "start_time": 101.003,
          "end_time": 102.718,
          "normalized_text": "it felt real in the mind."
        },
        {
          "id": 33,
          "lesson_id": 1,
          "index": 32,
          "text": "1982, Peter Gollwitzer wrote a whole book about this,",
          "translation": "Năm 1982, Peter Gollwitzer đã viết cả một cuốn sách về điều này,",
          "start_time": 102.74199999999999,
          "end_time": 105.23599999999999,
          "normalized_text": "1982, peter gollwitzer wrote a whole book about this,"
        },
        {
          "id": 34,
          "lesson_id": 1,
          "index": 33,
          "text": "and in 2009,",
          "translation": "và vào năm 2009,",
          "start_time": 105.25999999999999,
          "end_time": 106.803,
          "normalized_text": "and in 2009,"
        },
        {
          "id": 35,
          "lesson_id": 1,
          "index": 34,
          "text": "he did some new tests that were published.",
          "translation": "ông đã thực hiện một số bài kiểm tra mới đã được công bố.",
          "start_time": 106.827,
          "end_time": 109.374,
          "normalized_text": "he did some new tests that were published."
        },
        {
          "id": 36,
          "lesson_id": 1,
          "index": 35,
          "text": "It goes like this:",
          "translation": "Nó diễn ra như thế này:",
          "start_time": 109.398,
          "end_time": 110.866,
          "normalized_text": "it goes like this"
        },
        {
          "id": 37,
          "lesson_id": 1,
          "index": 36,
          "text": "163 people across four separate tests.",
          "translation": "163 người tham gia trong bốn bài kiểm tra riêng biệt.",
          "start_time": 110.89,
          "end_time": 113.88900000000001,
          "normalized_text": "163 people across four separate tests."
        },
        {
          "id": 38,
          "lesson_id": 1,
          "index": 37,
          "text": "Everyone wrote down their personal goal.",
          "translation": "Mọi người đều viết ra mục tiêu cá nhân của họ.",
          "start_time": 114.476,
          "end_time": 116.77000000000001,
          "normalized_text": "everyone wrote down their personal goal."
        },
        {
          "id": 39,
          "lesson_id": 1,
          "index": 38,
          "text": "Then half of them announced their commitment to this goal to the room,",
          "translation": "Sau đó, một nửa trong số họ công bố cam kết của mình đối với mục tiêu này cho cả phòng nghe,",
          "start_time": 116.794,
          "end_time": 120.681,
          "normalized_text": "then half of them announced their commitment to this goal to the room,"
        },
        {
          "id": 40,
          "lesson_id": 1,
          "index": 39,
          "text": "and half didn't.",
          "translation": "và nửa còn lại thì không.",
          "start_time": 120.705,
          "end_time": 121.887,
          "normalized_text": "and half did not."
        },
        {
          "id": 41,
          "lesson_id": 1,
          "index": 40,
          "text": "Then everyone was given 45 minutes of work",
          "translation": "Sau đó, mọi người được giao 45 phút làm việc",
          "start_time": 122.76,
          "end_time": 124.791,
          "normalized_text": "then everyone was given 45 minutes of work"
        },
        {
          "id": 42,
          "lesson_id": 1,
          "index": 41,
          "text": "that would directly lead them towards their goal,",
          "translation": "mà sẽ trực tiếp dẫn họ đến mục tiêu của mình,",
          "start_time": 124.815,
          "end_time": 127.11,
          "normalized_text": "that would directly lead them towards their goal,"
        },
        {
          "id": 43,
          "lesson_id": 1,
          "index": 42,
          "text": "but they were told that they could stop at any time.",
          "translation": "nhưng họ được cho biết rằng họ có thể dừng lại bất cứ lúc nào.",
          "start_time": 127.134,
          "end_time": 129.578,
          "normalized_text": "but they were told that they could stop at any time."
        },
        {
          "id": 44,
          "lesson_id": 1,
          "index": 43,
          "text": "Now, those who kept their mouths shut",
          "translation": "Giờ thì, những người đã giữ im lặng",
          "start_time": 129.602,
          "end_time": 131.485,
          "normalized_text": "now, those who kept their mouths shut"
        },
        {
          "id": 45,
          "lesson_id": 1,
          "index": 44,
          "text": "worked the entire 45 minutes on average,",
          "translation": "đã làm việc trung bình trọn vẹn 45 phút,",
          "start_time": 131.50900000000001,
          "end_time": 134.236,
          "normalized_text": "worked the entire 45 minutes on average,"
        },
        {
          "id": 46,
          "lesson_id": 1,
          "index": 45,
          "text": "and when asked afterward,",
          "translation": "và khi được hỏi sau đó,",
          "start_time": 134.26,
          "end_time": 135.797,
          "normalized_text": "and when asked afterward,"
        },
        {
          "id": 47,
          "lesson_id": 1,
          "index": 46,
          "text": "said that they felt that they had a long way to go still",
          "translation": "họ nói rằng họ cảm thấy mình vẫn còn một chặng đường dài phía trước",
          "start_time": 135.821,
          "end_time": 138.485,
          "normalized_text": "said that they felt that they had a long way to go still"
        },
        {
          "id": 48,
          "lesson_id": 1,
          "index": 47,
          "text": "to achieve their goal.",
          "translation": "để đạt được mục tiêu của mình.",
          "start_time": 138.50900000000001,
          "end_time": 139.662,
          "normalized_text": "to achieve their goal."
        },
        {
          "id": 49,
          "lesson_id": 1,
          "index": 48,
          "text": "But those who had announced it",
          "translation": "Nhưng những người đã công bố mục tiêu",
          "start_time": 139.686,
          "end_time": 141.236,
          "normalized_text": "but those who had announced it"
        },
        {
          "id": 50,
          "lesson_id": 1,
          "index": 49,
          "text": "quit after only 33 minutes, on average,",
          "translation": "đã bỏ cuộc trung bình chỉ sau 33 phút,",
          "start_time": 141.26,
          "end_time": 144.102,
          "normalized_text": "quit after only 33 minutes, on average,"
        },
        {
          "id": 51,
          "lesson_id": 1,
          "index": 50,
          "text": "and when asked afterward,",
          "translation": "và khi được hỏi sau đó,",
          "start_time": 144.126,
          "end_time": 145.856,
          "normalized_text": "and when asked afterward,"
        },
        {
          "id": 52,
          "lesson_id": 1,
          "index": 51,
          "text": "said that they felt much closer to achieving their goal.",
          "translation": "họ nói rằng họ cảm thấy gần hơn nhiều với việc đạt được mục tiêu của mình.",
          "start_time": 145.88,
          "end_time": 148.591,
          "normalized_text": "said that they felt much closer to achieving their goal."
        },
        {
          "id": 53,
          "lesson_id": 1,
          "index": 52,
          "text": "So if this is true, what can we do?",
          "translation": "Vậy nếu điều này là đúng, chúng ta có thể làm gì?",
          "start_time": 148.615,
          "end_time": 151.272,
          "normalized_text": "so if this is true, what can we do?"
        },
        {
          "id": 54,
          "lesson_id": 1,
          "index": 53,
          "text": "Well, you could resist the temptation to announce your goal.",
          "translation": "À, bạn có thể chống lại sự cám dỗ muốn công bố mục tiêu của mình.",
          "start_time": 151.899,
          "end_time": 155.497,
          "normalized_text": "well, you could resist the temptation to announce your goal."
        },
        {
          "id": 55,
          "lesson_id": 1,
          "index": 54,
          "text": "You can delay the gratification that the social acknowledgment brings,",
          "translation": "Bạn có thể trì hoãn sự thỏa mãn mà sự công nhận của xã hội mang lại,",
          "start_time": 156.26,
          "end_time": 160.54399999999998,
          "normalized_text": "you can delay the gratification that the social acknowledgment brings,"
        },
        {
          "id": 56,
          "lesson_id": 1,
          "index": 55,
          "text": "and you can understand that your mind mistakes the talking for the doing.",
          "translation": "và bạn có thể hiểu rằng tâm trí của bạn nhầm lẫn giữa việc nói và việc làm.",
          "start_time": 160.56799999999998,
          "end_time": 164.348,
          "normalized_text": "and you can understand that your mind mistakes the talking for the doing."
        },
        {
          "id": 57,
          "lesson_id": 1,
          "index": 56,
          "text": "But if you do need to talk about something,",
          "translation": "Nhưng nếu bạn thực sự cần nói về điều gì đó,",
          "start_time": 164.959,
          "end_time": 167.308,
          "normalized_text": "but if you do need to talk about something,"
        },
        {
          "id": 58,
          "lesson_id": 1,
          "index": 57,
          "text": "you can state it in a way that gives you no satisfaction,",
          "translation": "bạn có thể trình bày nó theo cách không mang lại cho bạn sự thỏa mãn nào,",
          "start_time": 167.332,
          "end_time": 171.679,
          "normalized_text": "you can state it in a way that gives you no satisfaction,"
        },
        {
          "id": 59,
          "lesson_id": 1,
          "index": 58,
          "text": "such as, \"I really want to run this marathon,",
          "translation": "chẳng hạn như, \"Tôi thực sự muốn chạy marathon,",
          "start_time": 171.703,
          "end_time": 173.822,
          "normalized_text": "such as, i really want to run this marathon,"
        },
        {
          "id": 60,
          "lesson_id": 1,
          "index": 59,
          "text": "so I need to train five times a week",
          "translation": "vì vậy tôi cần phải luyện tập năm lần một tuần",
          "start_time": 173.846,
          "end_time": 175.576,
          "normalized_text": "so i need to train five times a week"
        },
        {
          "id": 61,
          "lesson_id": 1,
          "index": 60,
          "text": "and kick my ass if I don't, okay?\"",
          "translation": "và hãy thúc ép tôi nếu tôi không làm vậy, được chứ?\"",
          "start_time": 175.6,
          "end_time": 177.303,
          "normalized_text": "and kick my ass if i do not, okay?"
        },
        {
          "id": 62,
          "lesson_id": 1,
          "index": 61,
          "text": "So audience, next time you're tempted to tell someone your goal,",
          "translation": "Vậy thưa quý vị khán giả, lần tới khi bạn muốn nói cho ai đó biết mục tiêu của mình,",
          "start_time": 177.97,
          "end_time": 181.071,
          "normalized_text": "so audience, next time you are tempted to tell someone your goal,"
        },
        {
          "id": 63,
          "lesson_id": 1,
          "index": 62,
          "text": "what will you say?",
          "translation": "bạn sẽ nói gì?",
          "start_time": 181.095,
          "end_time": 182.245,
          "normalized_text": "what will you say?"
        },
        {
          "id": 64,
          "lesson_id": 1,
          "index": 63,
          "text": "Exactly! Well done.",
          "translation": "Chính xác! Làm tốt lắm.",
          "start_time": 183.294,
          "end_time": 184.546,
          "normalized_text": "exactly! well done."
        }
      ],
      "created_at": "2025-11-07T21:47:03+0700",
      "updated_at": "2025-11-07T21:48:04+0700"
    }
  ]
}

